MANIFEST.in
README.md
setup.cfg
setup.py
dempy/MatrixGenerator.py
dempy/Qgis_tool.py
dempy/__init__.py
dempy/fftdem.py
dempy/lidar.py
dempy/morphometry.py
dempy/plotting.py
dempy/pointcloud.py
dempy/rasterTool.py
dempy/shp_func.py
dempy.egg-info/PKG-INFO
dempy.egg-info/SOURCES.txt
dempy.egg-info/dependency_links.txt
dempy.egg-info/requires.txt
dempy.egg-info/top_level.txt
dempy/decomposition/diamondSquare.c
dempy/decomposition/diamondSquare.pyx
dempy/snow/tabler.c
dempy/snow/tabler.pyx
dempy/snow/winstral.c
dempy/snow/winstral.pyx